<Media type="AEP" stringCount="826">
	<String id="ButtonOrLink.Account.Billing" source="Billing">Billing</String>
	<String id="ButtonOrLink.Campaign.ViewCampaignInfluenceReport" source="View Campaign Influence Report">View Campaign Influence Report</String>
	<String id="ButtonOrLink.Case.UpsellCrosssellOpportunity" source="Up-sell / Cross-sell Opportunity">Up-sell / Cross-sell Opportunity</String>
	<String id="ButtonOrLink.Opportunity.DeliveryStatus" source="Delivery Status">Delivery Status</String>
	<String id="CustomField.Account.Active.FieldLabel" source="Active">Active</String>
	<String id="CustomField.Account.CustomerPriority.FieldLabel" source="Customer Priority">Customer Priority</String>
	<String id="CustomField.Account.CustomerPriority.HelpText" source="HelpText for CustomerPriority">HelpText for CustomerPriority</String>
	<String id="CustomField.Account.NumberofLocations.FieldLabel" source="Number of Locations">Number of Locations</String>
	<String id="CustomField.Account.SLA.FieldLabel" source="SLA">SLA</String>
	<String id="CustomField.Account.SLAExpirationDate.FieldLabel" source="SLA Expiration Date">SLA Expiration Date</String>
	<String id="CustomField.Account.SLASerialNumber.FieldLabel" source="SLA Serial Number">SLA Serial Number</String>
	<String id="CustomField.Account.UpsellOpportunity.FieldLabel" source="Upsell Opportunity">Upsell Opportunity</String>
	<String id="CustomField.Case.EngineeringReqNumber.FieldLabel" source="Engineering Req Number">Engineering Req Number</String>
	<String id="CustomField.Case.PotentialLiability.FieldLabel" source="Potential Liability">Potential Liability</String>
	<String id="CustomField.Case.Product.FieldLabel" source="Product">Product</String>
	<String id="CustomField.Case.SLAViolation.FieldLabel" source="SLA Violation">SLA Violation</String>
	<String id="CustomField.Contact.Languages.FieldLabel" source="Languages">Languages</String>
	<String id="CustomField.Contact.Level.FieldLabel" source="Level">Level</String>
	<String id="CustomField.Goal.OrigGoalId.FieldLabel" source="OrigGoalId">OrigGoalId</String>
	<String id="CustomField.Lead.CurrentGenerators.FieldLabel" source="Current Generator(s)">Current Generator(s)</String>
	<String id="CustomField.Lead.NumberofLocations.FieldLabel" source="Number of Locations">Number of Locations</String>
	<String id="CustomField.Lead.Primary.FieldLabel" source="Primary">Primary</String>
	<String id="CustomField.Lead.ProductInterest.FieldLabel" source="Product Interest">Product Interest</String>
	<String id="CustomField.Lead.SICCode.FieldLabel" source="SIC Code">SIC Code</String>
	<String id="CustomField.Metric.OrigMetricId.FieldLabel" source="OrigMetricId">OrigMetricId</String>
	<String id="CustomField.Opportunity.CurrentGenerators.FieldLabel" source="Current Generator(s)">Current Generator(s)</String>
	<String id="CustomField.Opportunity.DeliveryInstallationStatus.FieldLabel" source="Delivery/Installation Status">Delivery/Installation Status</String>
	<String id="CustomField.Opportunity.MainCompetitors.FieldLabel" source="Main Competitor(s)">Main Competitor(s)</String>
	<String id="CustomField.Opportunity.OrderNumber.FieldLabel" source="Order Number">Order Number</String>
	<String id="CustomField.Opportunity.TrackingNumber.FieldLabel" source="Tracking Number">Tracking Number</String>
	<String id="CustomReportType.screen_flows_prebuilt_crt.Name" source="Screen Flows">Screen Flows</String>
	<String id="CustomReportType.screen_flows_prebuilt_crt.Description" source="Find out which flows get executed and how long users take to complete each flow screen.">Find out which flows get executed and how long users take to complete each flow screen.</String>
	<String id="CrtLayoutSection.screen_flows_prebuilt_crt_1" source="Flow Interview Logs">Flow Interview Logs</String>
	<String id="CrtLayoutSection.screen_flows_prebuilt_crt_2" source="Flow Interview Log Entries">Flow Interview Log Entries</String>
	<String id="LayoutSection.AlternativePaymentMethod.Alternative Payment Method Layout.Alternative Payment Method_0" source="Alternative Payment Method">Alternative Payment Method</String>
	<String id="LayoutSection.ApiAnomalyEventStore.API Anomaly Event Store Layout.System Information_2" source="System Information">System Information</String>
	<String id="LayoutSection.CardPaymentMethod.Card Payment Method Layout.Card Payment Method_0" source="Card Payment Method">Card Payment Method</String>
	<String id="LayoutSection.CommunityMemberLayout.Community Member Layout.Basic Information_0" source="Basic Information">Basic Information</String>
	<String id="LayoutSection.CommunityMemberLayout.Community Member Layout.Chatter Settings_2" source="Chatter Settings">Chatter Settings</String>
	<String id="LayoutSection.CommunityMemberLayout.Community Member Layout.Language And Locale Settings_1" source="Language And Locale Settings">Language And Locale Settings</String>
	<String id="LayoutSection.CredentialStuffingEventStore.Credential Stuffing Event Store Layout.System Information_2" source="System Information">System Information</String>
	<String id="LayoutSection.DigitalWallet.Digital Wallet Layout.Digital Wallet_0" source="Digital Wallet">Digital Wallet</String>
	<String id="LayoutSection.FulfillmentOrder.Fulfillment Order Layout.Fulfillment Order Information_0" source="Fulfillment Order Information">Fulfillment Order Information</String>
	<String id="LayoutSection.FulfillmentOrderItemAdjustment.Fulfillment Order Item Adjustment Layout.Fulfillment Order Item Adjustment Information_0" source="Fulfillment Order Item Adjustment Information">Fulfillment Order Item Adjustment Information</String>
	<String id="LayoutSection.FulfillmentOrderItemTax.Fulfillment Order Item Tax Layout.Fulfillment Order Item Tax Information_0" source="Fulfillment Order Item Tax Information">Fulfillment Order Item Tax Information</String>
	<String id="LayoutSection.OrderAdjustmentGroup.Order Adjustment Group Layout.Order Adjustment Group Information_0" source="Order Adjustment Group Information">Order Adjustment Group Information</String>
	<String id="LayoutSection.OrderAdjustmentGroupSummary.Order Adjustment Group Summary Layout.Order Adjustment Group Summary Information_0" source="Order Adjustment Group Summary Information">Order Adjustment Group Summary Information</String>
	<String id="LayoutSection.OrderDeliveryGroup.Order Delivery Group Layout.Financial Information_1" source="Financial Information">Financial Information</String>
	<String id="LayoutSection.OrderDeliveryGroup.Order Delivery Group Layout.Order Delivery Group Information_0" source="Order Delivery Group Information">Order Delivery Group Information</String>
	<String id="LayoutSection.OrderDeliveryGroupSummary.Order Delivery Group Summary Layout.Order Delivery Group Summary Information_0" source="Order Delivery Group Summary Information">Order Delivery Group Summary Information</String>
	<String id="LayoutSection.OrderDeliveryMethod.Order Delivery Method Layout.Order Delivery Method Information_0" source="Order Delivery Method Information">Order Delivery Method Information</String>
	<String id="LayoutSection.OrderItemAdjustmentLineItem.Order Product Adjustment Line Item Layout.Order Product Adjustment Line Item Information_0" source="Order Product Adjustment Line Item Information">Order Product Adjustment Line Item Information</String>
	<String id="LayoutSection.OrderItemSummary.Order Product Summary Layout.Order Product Summary_0" source="Order Product Summary">Order Product Summary</String>
	<String id="LayoutSection.OrderItemTaxLineItem.Order Product Tax Line Item Layout.Order Product Tax Line Item Information_0" source="Order Product Tax Line Item Information">Order Product Tax Line Item Information</String>
	<String id="LayoutSection.OrderPaymentSummary.Order Payment Summary Layout.Order Payment Summary Amounts_1" source="Order Payment Summary Amounts">Order Payment Summary Amounts</String>
	<String id="LayoutSection.OrderPaymentSummary.Order Payment Summary Layout.Order Payment Summary Information_0" source="Order Payment Summary Information">Order Payment Summary Information</String>
	<String id="LayoutSection.PaymentGateway.Payment Gateway Layout.Payment Gateway_0" source="Payment Gateway">Payment Gateway</String>
	<String id="LayoutSection.PaymentGroup.Payment Group Layout.Payment Group_0" source="Payment Group">Payment Group</String>
	<String id="LayoutSection.ReportAnomalyEventStore.Report Anomaly Event Store Layout.System Information_2" source="System Information">System Information</String>
	<String id="LayoutSection.ReturnOrderItemAdjustment.Return Order Item Adjustment Layout.Return Order Item Adjustment Information_0" source="Return Order Item Adjustment Information">Return Order Item Adjustment Information</String>
	<String id="LayoutSection.ReturnOrderItemAdjustment.Return Order Item Adjustment Layout.Return Order Item Adjustment Totals_1" source="Return Order Item Adjustment Totals">Return Order Item Adjustment Totals</String>
	<String id="LayoutSection.ReturnOrderItemTax.Return Order Item Tax Layout.Return Order Item Tax Information_0" source="Return Order Item Tax Information">Return Order Item Tax Information</String>
	<String id="LayoutSection.SalesChannel.Sales Channel Layout.Sales Channel Information_0" source="Sales Channel Information">Sales Channel Information</String>
	<String id="LayoutSection.SessionHijackingEventStore.Session Hijacking Event Store Layout.System Information_2" source="System Information">System Information</String>
	<String id="LayoutSection.WorkCoaching.Coaching Layout.Coaching Information_0" source="Coaching Information">Coaching Information</String>
	<String id="PicklistValue.Account.Active.No" source="No">No</String>
	<String id="PicklistValue.Account.Active.Yes" source="Yes">Yes</String>
	<String id="PicklistValue.Account.CustomerPriority.High" source="High">High</String>
	<String id="PicklistValue.Account.CustomerPriority.Low" source="Low">Low</String>
	<String id="PicklistValue.Account.CustomerPriority.Medium" source="Medium">Medium</String>
	<String id="PicklistValue.Account.SLA.Bronze" source="Bronze">Bronze</String>
	<String id="PicklistValue.Account.SLA.Gold" source="Gold">Gold</String>
	<String id="PicklistValue.Account.SLA.Platinum" source="Platinum">Platinum</String>
	<String id="PicklistValue.Account.SLA.Silver" source="Silver">Silver</String>
	<String id="PicklistValue.Account.UpsellOpportunity.Maybe" source="Maybe">Maybe</String>
	<String id="PicklistValue.Account.UpsellOpportunity.No" source="No">No</String>
	<String id="PicklistValue.Account.UpsellOpportunity.Yes" source="Yes">Yes</String>
	<String id="PicklistValue.Case.PotentialLiability.No" source="No">No</String>
	<String id="PicklistValue.Case.PotentialLiability.Yes" source="Yes">Yes</String>
	<String id="PicklistValue.Case.Product.GC1020" source="GC1020">GC1020</String>
	<String id="PicklistValue.Case.Product.GC1040" source="GC1040">GC1040</String>
	<String id="PicklistValue.Case.Product.GC1060" source="GC1060">GC1060</String>
	<String id="PicklistValue.Case.Product.GC3020" source="GC3020">GC3020</String>
	<String id="PicklistValue.Case.Product.GC3040" source="GC3040">GC3040</String>
	<String id="PicklistValue.Case.Product.GC3060" source="GC3060">GC3060</String>
	<String id="PicklistValue.Case.Product.GC5020" source="GC5020">GC5020</String>
	<String id="PicklistValue.Case.Product.GC5040" source="GC5040">GC5040</String>
	<String id="PicklistValue.Case.Product.GC5060" source="GC5060">GC5060</String>
	<String id="PicklistValue.Case.SLAViolation.No" source="No">No</String>
	<String id="PicklistValue.Case.SLAViolation.Yes" source="Yes">Yes</String>
	<String id="PicklistValue.Contact.Level.Primary" source="Primary">Primary</String>
	<String id="PicklistValue.Contact.Level.Secondary" source="Secondary">Secondary</String>
	<String id="PicklistValue.Contact.Level.Tertiary" source="Tertiary">Tertiary</String>
	<String id="PicklistValue.Lead.Primary.No" source="No">No</String>
	<String id="PicklistValue.Lead.Primary.Yes" source="Yes">Yes</String>
	<String id="PicklistValue.Lead.ProductInterest.GC1000 series" source="GC1000 series">GC1000 series</String>
	<String id="PicklistValue.Lead.ProductInterest.GC3000 series" source="GC3000 series">GC3000 series</String>
	<String id="PicklistValue.Lead.ProductInterest.GC5000 series" source="GC5000 series">GC5000 series</String>
	<String id="PicklistValue.Opportunity.DeliveryInstallationStatus.Completed" source="Completed">Completed</String>
	<String id="PicklistValue.Opportunity.DeliveryInstallationStatus.In progress" source="In progress">In progress</String>
	<String id="PicklistValue.Opportunity.DeliveryInstallationStatus.Yet to begin" source="Yet to begin">Yet to begin</String>
	<String id="PicklistValue.Standard.accountOwnership.Other" source="Other">Other</String>
	<String id="PicklistValue.Standard.accountOwnership.Private" source="Private">Private</String>
	<String id="PicklistValue.Standard.accountOwnership.Public" source="Public">Public</String>
	<String id="PicklistValue.Standard.accountOwnership.Subsidiary" source="Subsidiary">Subsidiary</String>
	<String id="PicklistValue.Standard.opportunityType.Existing Customer - Downgrade" source="Existing Customer - Downgrade">Existing Customer - Downgrade</String>
	<String id="PicklistValue.Standard.opportunityType.Existing Customer - Replacement" source="Existing Customer - Replacement">Existing Customer - Replacement</String>
	<String id="PicklistValue.Standard.opportunityType.Existing Customer - Upgrade" source="Existing Customer - Upgrade">Existing Customer - Upgrade</String>
	<String id="PicklistValue.Standard.opportunityType.New Customer" source="New Customer">New Customer</String>
	<String id="PicklistValue.Standard.returnOrderStatus.Approved" source="Approved">Approved</String>
	<String id="PicklistValue.Standard.returnOrderStatus.Canceled" source="Canceled">Canceled</String>
	<String id="PicklistValue.Standard.returnOrderStatus.Closed" source="Closed">Closed</String>
	<String id="PicklistValue.Standard.returnOrderStatus.Draft" source="Draft">Draft</String>
	<String id="PicklistValue.Standard.returnOrderStatus.Submitted" source="Submitted">Submitted</String>
	<String id="PicklistValue.Standard.returnOrderShipmentType.Next Business Day" source="Next Business Day">Next Business Day</String>
	<String id="PicklistValue.Standard.returnOrderShipmentType.Overnight" source="Overnight">Overnight</String>
	<String id="PicklistValue.Standard.returnOrderShipmentType.Pick Up" source="Pick Up">Pick Up</String>
	<String id="PicklistValue.Standard.returnOrderShipmentType.Rush" source="Rush">Rush</String>
	<String id="PicklistValue.Standard.returnOrderShipmentType.Standard" source="Standard">Standard</String>
	<String id="PicklistValue.Standard.ageOver.13 or Older" source="13 or Older">13 or Older</String>
	<String id="PicklistValue.Standard.ageOver.16 or Older" source="16 or Older">16 or Older</String>
	<String id="PicklistValue.Standard.contactRole.Business User" source="Business User">Business User</String>
	<String id="PicklistValue.Standard.contactRole.Decision Maker" source="Decision Maker">Decision Maker</String>
	<String id="PicklistValue.Standard.contactRole.Economic Buyer" source="Economic Buyer">Economic Buyer</String>
	<String id="PicklistValue.Standard.contactRole.Economic Decision Maker" source="Economic Decision Maker">Economic Decision Maker</String>
	<String id="PicklistValue.Standard.contactRole.Evaluator" source="Evaluator">Evaluator</String>
	<String id="PicklistValue.Standard.contactRole.Executive Sponsor" source="Executive Sponsor">Executive Sponsor</String>
	<String id="PicklistValue.Standard.contactRole.Influencer" source="Influencer">Influencer</String>
	<String id="PicklistValue.Standard.contactRole.Other" source="Other">Other</String>
	<String id="PicklistValue.Standard.contactRole.Technical Buyer" source="Technical Buyer">Technical Buyer</String>
	<String id="PicklistValue.Standard.returnOrderLineItemProcessPlan.Discard" source="Discard">Discard</String>
	<String id="PicklistValue.Standard.returnOrderLineItemProcessPlan.Repair" source="Repair">Repair</String>
	<String id="PicklistValue.Standard.returnOrderLineItemProcessPlan.Restock" source="Restock">Restock</String>
	<String id="PicklistValue.Standard.returnOrderLineItemProcessPlan.Salvage" source="Salvage">Salvage</String>
	<String id="PicklistValue.Standard.returnOrderLineItemReasonForReturn.Damaged" source="Damaged">Damaged</String>
	<String id="PicklistValue.Standard.returnOrderLineItemReasonForReturn.Defective" source="Defective">Defective</String>
	<String id="PicklistValue.Standard.returnOrderLineItemReasonForReturn.Duplicate Order" source="Duplicate Order">Duplicate Order</String>
	<String id="PicklistValue.Standard.returnOrderLineItemReasonForReturn.Not Satisfied" source="Not Satisfied">Not Satisfied</String>
	<String id="PicklistValue.Standard.returnOrderLineItemReasonForReturn.Other" source="Other">Other</String>
	<String id="PicklistValue.Standard.returnOrderLineItemReasonForReturn.Outdated" source="Outdated">Outdated</String>
	<String id="PicklistValue.Standard.returnOrderLineItemReasonForReturn.Wrong Item" source="Wrong Item">Wrong Item</String>
	<String id="PicklistValue.Standard.returnOrderLineItemReasonForReturn.Wrong Quantity" source="Wrong Quantity">Wrong Quantity</String>
	<String id="PicklistValue.Standard.returnOrderLineItemRepaymentMethod.Credit" source="Credit">Credit</String>
	<String id="PicklistValue.Standard.returnOrderLineItemRepaymentMethod.Refund" source="Refund">Refund</String>
	<String id="PicklistValue.Standard.returnOrderLineItemRepaymentMethod.Replace" source="Replace">Replace</String>
	<String id="PicklistValue.Standard.returnOrderLineItemRepaymentMethod.Return" source="Return">Return</String>
	<String id="PicklistValue.Standard.caseType.Electrical" source="Electrical">Electrical</String>
	<String id="PicklistValue.Standard.caseType.Electronic" source="Electronic">Electronic</String>
	<String id="PicklistValue.Standard.caseType.Mechanical" source="Mechanical">Mechanical</String>
	<String id="PicklistValue.Standard.caseType.Other" source="Other">Other</String>
	<String id="PicklistValue.Standard.caseType.Structural" source="Structural">Structural</String>
	<String id="PicklistValue.Standard.contactRequestStatus.Abandoned" source="Abandoned">Abandoned</String>
	<String id="PicklistValue.Standard.contactRequestStatus.Attempted" source="Attempted">Attempted</String>
	<String id="PicklistValue.Standard.contactRequestStatus.Contacted" source="Contacted">Contacted</String>
	<String id="PicklistValue.Standard.contactRequestStatus.New" source="New">New</String>
	<String id="PicklistValue.Standard.contactRequestRequestedChannel.Phone" source="Phone">Phone</String>
	<String id="PicklistValue.Standard.caseOrigin.Email" source="Email">Email</String>
	<String id="PicklistValue.Standard.caseOrigin.Phone" source="Phone">Phone</String>
	<String id="PicklistValue.Standard.caseOrigin.Web" source="Web">Web</String>
	<String id="PicklistValue.Standard.contactRequestReason.Account" source="Account">Account</String>
	<String id="PicklistValue.Standard.contactRequestReason.Billing" source="Billing">Billing</String>
	<String id="PicklistValue.Standard.contactRequestReason.Case" source="Case">Case</String>
	<String id="PicklistValue.Standard.contactRequestReason.General" source="General">General</String>
	<String id="PicklistValue.Standard.contactRequestReason.Order" source="Order">Order</String>
	<String id="PicklistValue.Standard.contactRequestReason.Other" source="Other">Other</String>
	<String id="PicklistValue.Standard.contactRequestReason.Product" source="Product">Product</String>
	<String id="PicklistValue.Standard.caseReason.Breakdown" source="Breakdown">Breakdown</String>
	<String id="PicklistValue.Standard.caseReason.Equipment Complexity" source="Equipment Complexity">Equipment Complexity</String>
	<String id="PicklistValue.Standard.caseReason.Equipment Design" source="Equipment Design">Equipment Design</String>
	<String id="PicklistValue.Standard.caseReason.Feedback" source="Feedback">Feedback</String>
	<String id="PicklistValue.Standard.caseReason.Installation" source="Installation">Installation</String>
	<String id="PicklistValue.Standard.caseReason.Other" source="Other">Other</String>
	<String id="PicklistValue.Standard.caseReason.Performance" source="Performance">Performance</String>
	<String id="PicklistValue.Standard.partnerRole.Advertiser" source="Advertiser">Advertiser</String>
	<String id="PicklistValue.Standard.partnerRole.Agency" source="Agency">Agency</String>
	<String id="PicklistValue.Standard.partnerRole.Broker" source="Broker">Broker</String>
	<String id="PicklistValue.Standard.partnerRole.Consultant" source="Consultant">Consultant</String>
	<String id="PicklistValue.Standard.partnerRole.Contractor" source="Contractor">Contractor</String>
	<String id="PicklistValue.Standard.partnerRole.Dealer" source="Dealer">Dealer</String>
	<String id="PicklistValue.Standard.partnerRole.Developer" source="Developer">Developer</String>
	<String id="PicklistValue.Standard.partnerRole.Distributor" source="Distributor">Distributor</String>
	<String id="PicklistValue.Standard.partnerRole.Institution" source="Institution">Institution</String>
	<String id="PicklistValue.Standard.partnerRole.Lender" source="Lender">Lender</String>
	<String id="PicklistValue.Standard.partnerRole.Supplier" source="Supplier">Supplier</String>
	<String id="PicklistValue.Standard.partnerRole.System Integrator" source="System Integrator">System Integrator</String>
	<String id="PicklistValue.Standard.partnerRole.VAR/Reseller" source="VAR/Reseller">VAR/Reseller</String>
	<String id="PicklistValue.Standard.securityClassification.Confidential" source="Confidential">Confidential</String>
	<String id="PicklistValue.Standard.securityClassification.Internal" source="Internal">Internal</String>
	<String id="PicklistValue.Standard.securityClassification.MissionCritical" source="MissionCritical">MissionCritical</String>
	<String id="PicklistValue.Standard.securityClassification.Public" source="Public">Public</String>
	<String id="PicklistValue.Standard.securityClassification.Restricted" source="Restricted">Restricted</String>
	<String id="PicklistValue.Standard.leadStatus.Closed - Converted" source="Closed - Converted">Closed - Converted</String>
	<String id="PicklistValue.Standard.leadStatus.Closed - Not Converted" source="Closed - Not Converted">Closed - Not Converted</String>
	<String id="PicklistValue.Standard.leadStatus.Open - Not Contacted" source="Open - Not Contacted">Open - Not Contacted</String>
	<String id="PicklistValue.Standard.leadStatus.Working - Contacted" source="Working - Contacted">Working - Contacted</String>
	<String id="PicklistValue.Standard.caseStatus.Closed" source="Closed">Closed</String>
	<String id="PicklistValue.Standard.caseStatus.Escalated" source="Escalated">Escalated</String>
	<String id="PicklistValue.Standard.caseStatus.New" source="New">New</String>
	<String id="PicklistValue.Standard.caseStatus.Working" source="Working">Working</String>
	<String id="PicklistValue.Standard.accountRating.Cold" source="Cold">Cold</String>
	<String id="PicklistValue.Standard.accountRating.Hot" source="Hot">Hot</String>
	<String id="PicklistValue.Standard.accountRating.Warm" source="Warm">Warm</String>
	<String id="PicklistValue.Standard.casePriority.High" source="High">High</String>
	<String id="PicklistValue.Standard.casePriority.Low" source="Low">Low</String>
	<String id="PicklistValue.Standard.casePriority.Medium" source="Medium">Medium</String>
	<String id="PicklistValue.Standard.solutionStatus.Draft" source="Draft">Draft</String>
	<String id="PicklistValue.Standard.solutionStatus.Duplicate" source="Duplicate">Duplicate</String>
	<String id="PicklistValue.Standard.solutionStatus.Reviewed" source="Reviewed">Reviewed</String>
	<String id="PicklistValue.Standard.taskStatus.Completed" source="Completed">Completed</String>
	<String id="PicklistValue.Standard.taskStatus.Deferred" source="Deferred">Deferred</String>
	<String id="PicklistValue.Standard.taskStatus.In Progress" source="In Progress">In Progress</String>
	<String id="PicklistValue.Standard.taskStatus.Not Started" source="Not Started">Not Started</String>
	<String id="PicklistValue.Standard.taskStatus.Waiting on someone else" source="Waiting on someone else">Waiting on someone else</String>
	<String id="PicklistValue.Standard.opportunityStage.Closed Lost" source="Closed Lost">Closed Lost</String>
	<String id="PicklistValue.Standard.opportunityStage.Closed Won" source="Closed Won">Closed Won</String>
	<String id="PicklistValue.Standard.opportunityStage.Id. Decision Makers" source="Id. Decision Makers">Id. Decision Makers</String>
	<String id="PicklistValue.Standard.opportunityStage.Needs Analysis" source="Needs Analysis">Needs Analysis</String>
	<String id="PicklistValue.Standard.opportunityStage.Negotiation/Review" source="Negotiation/Review">Negotiation/Review</String>
	<String id="PicklistValue.Standard.opportunityStage.Perception Analysis" source="Perception Analysis">Perception Analysis</String>
	<String id="PicklistValue.Standard.opportunityStage.Proposal/Price Quote" source="Proposal/Price Quote">Proposal/Price Quote</String>
	<String id="PicklistValue.Standard.opportunityStage.Prospecting" source="Prospecting">Prospecting</String>
	<String id="PicklistValue.Standard.opportunityStage.Qualification" source="Qualification">Qualification</String>
	<String id="PicklistValue.Standard.opportunityStage.Value Proposition" source="Value Proposition">Value Proposition</String>
	<String id="PicklistValue.Standard.militaryService.No" source="No">No</String>
	<String id="PicklistValue.Standard.militaryService.Unknown" source="Unknown">Unknown</String>
	<String id="PicklistValue.Standard.militaryService.Yes" source="Yes">Yes</String>
	<String id="PicklistValue.Standard.fulfillmentType.Download" source="Download">Download</String>
	<String id="PicklistValue.Standard.fulfillmentType.Email" source="Email">Email</String>
	<String id="PicklistValue.Standard.fulfillmentType.In Store Pickup" source="In Store Pickup">In Store Pickup</String>
	<String id="PicklistValue.Standard.fulfillmentType.Retail Store" source="Retail Store">Retail Store</String>
	<String id="PicklistValue.Standard.fulfillmentType.Supplier" source="Supplier">Supplier</String>
	<String id="PicklistValue.Standard.fulfillmentType.Warehouse" source="Warehouse">Warehouse</String>
	<String id="PicklistValue.Standard.fulfillmentStatus.Allocated" source="Allocated">Allocated</String>
	<String id="PicklistValue.Standard.fulfillmentStatus.Assigned" source="Assigned">Assigned</String>
	<String id="PicklistValue.Standard.fulfillmentStatus.Cancelled" source="Cancelled">Cancelled</String>
	<String id="PicklistValue.Standard.fulfillmentStatus.Draft" source="Draft">Draft</String>
	<String id="PicklistValue.Standard.fulfillmentStatus.Fulfilled" source="Fulfilled">Fulfilled</String>
	<String id="PicklistValue.Standard.fulfillmentStatus.Pickpack" source="Pickpack">Pickpack</String>
	<String id="PicklistValue.Standard.orderItemType.Delivery Charge" source="Delivery Charge">Delivery Charge</String>
	<String id="PicklistValue.Standard.orderItemType.Order Product" source="Order Product">Order Product</String>
	<String id="PicklistValue.Standard.campaignType.Advertisement" source="Advertisement">Advertisement</String>
	<String id="PicklistValue.Standard.campaignType.Banner Ads" source="Banner Ads">Banner Ads</String>
	<String id="PicklistValue.Standard.campaignType.Conference" source="Conference">Conference</String>
	<String id="PicklistValue.Standard.campaignType.Direct Mail" source="Direct Mail">Direct Mail</String>
	<String id="PicklistValue.Standard.campaignType.Email" source="Email">Email</String>
	<String id="PicklistValue.Standard.campaignType.Other" source="Other">Other</String>
	<String id="PicklistValue.Standard.campaignType.Partners" source="Partners">Partners</String>
	<String id="PicklistValue.Standard.campaignType.Public Relations" source="Public Relations">Public Relations</String>
	<String id="PicklistValue.Standard.campaignType.Referral Program" source="Referral Program">Referral Program</String>
	<String id="PicklistValue.Standard.campaignType.Telemarketing" source="Telemarketing">Telemarketing</String>
	<String id="PicklistValue.Standard.campaignType.Trade Show" source="Trade Show">Trade Show</String>
	<String id="PicklistValue.Standard.campaignType.Webinar" source="Webinar">Webinar</String>
	<String id="PicklistValue.Standard.campaignStatus.Aborted" source="Aborted">Aborted</String>
	<String id="PicklistValue.Standard.campaignStatus.Completed" source="Completed">Completed</String>
	<String id="PicklistValue.Standard.campaignStatus.In Progress" source="In Progress">In Progress</String>
	<String id="PicklistValue.Standard.campaignStatus.Planned" source="Planned">Planned</String>
	<String id="PicklistValue.Standard.buyerAccountStatus.Active" source="Active">Active</String>
	<String id="PicklistValue.Standard.buyerAccountStatus.Inactive" source="Inactive">Inactive</String>
	<String id="PicklistValue.Standard.buyerAccountStatus.On Hold" source="On Hold">On Hold</String>
	<String id="PicklistValue.Standard.buyerAccountStatus.Pending" source="Pending">Pending</String>
	<String id="PicklistValue.Standard.buyerAccountCreditStatus.Bad Credit" source="Bad Credit">Bad Credit</String>
	<String id="PicklistValue.Standard.buyerAccountCreditStatus.Delinquent" source="Delinquent">Delinquent</String>
	<String id="PicklistValue.Standard.buyerAccountCreditStatus.Good Credit" source="Good Credit">Good Credit</String>
	<String id="PicklistValue.Standard.buyerAccountCreditStatus.On Hold" source="On Hold">On Hold</String>
	<String id="PicklistValue.Standard.contractStatus.Activated" source="Activated">Activated</String>
	<String id="PicklistValue.Standard.contractStatus.Draft" source="Draft">Draft</String>
	<String id="PicklistValue.Standard.contractStatus.In Approval Process" source="In Approval Process">In Approval Process</String>
	<String id="PicklistValue.Standard.buyerAccountCommerceType.Buyer" source="Buyer">Buyer</String>
	<String id="PicklistValue.Standard.buyerAccountCommerceType.Reseller" source="Reseller">Reseller</String>
	<String id="PicklistValue.Standard.buyerAccountCommerceType.Seller" source="Seller">Seller</String>
	<String id="PicklistValue.Standard.shiftStatus.Confirmed" source="Confirmed">Confirmed</String>
	<String id="PicklistValue.Standard.shiftStatus.Published" source="Published">Published</String>
	<String id="PicklistValue.Standard.shiftStatus.Tentative" source="Tentative">Tentative</String>
	<String id="PicklistValue.Standard.accountType.Channel Partner / Reseller" source="Channel Partner / Reseller">Channel Partner / Reseller</String>
	<String id="PicklistValue.Standard.accountType.Customer - Channel" source="Customer - Channel">Customer - Channel</String>
	<String id="PicklistValue.Standard.accountType.Customer - Direct" source="Customer - Direct">Customer - Direct</String>
	<String id="PicklistValue.Standard.accountType.Installation Partner" source="Installation Partner">Installation Partner</String>
	<String id="PicklistValue.Standard.accountType.Other" source="Other">Other</String>
	<String id="PicklistValue.Standard.accountType.Prospect" source="Prospect">Prospect</String>
	<String id="PicklistValue.Standard.accountType.Technology Partner" source="Technology Partner">Technology Partner</String>
	<String id="PicklistValue.Standard.eventType.Call" source="Call">Call</String>
	<String id="PicklistValue.Standard.eventType.Email" source="Email">Email</String>
	<String id="PicklistValue.Standard.eventType.Meeting" source="Meeting">Meeting</String>
	<String id="PicklistValue.Standard.eventType.Other" source="Other">Other</String>
	<String id="PicklistValue.Standard.taskType.Call" source="Call">Call</String>
	<String id="PicklistValue.Standard.taskType.Email" source="Email">Email</String>
	<String id="PicklistValue.Standard.taskType.Meeting" source="Meeting">Meeting</String>
	<String id="PicklistValue.Standard.taskType.Other" source="Other">Other</String>
	<String id="PicklistValue.Standard.salesTeamRole.Account Manager" source="Account Manager">Account Manager</String>
	<String id="PicklistValue.Standard.salesTeamRole.Channel Manager" source="Channel Manager">Channel Manager</String>
	<String id="PicklistValue.Standard.salesTeamRole.Executive Sponsor" source="Executive Sponsor">Executive Sponsor</String>
	<String id="PicklistValue.Standard.salesTeamRole.Lead Qualifier" source="Lead Qualifier">Lead Qualifier</String>
	<String id="PicklistValue.Standard.salesTeamRole.Pre-Sales Consultant" source="Pre-Sales Consultant">Pre-Sales Consultant</String>
	<String id="PicklistValue.Standard.salesTeamRole.Sales Manager" source="Sales Manager">Sales Manager</String>
	<String id="PicklistValue.Standard.salesTeamRole.Sales Rep" source="Sales Rep">Sales Rep</String>
	<String id="PicklistValue.Standard.snippetType.Date" source="Date">Date</String>
	<String id="PicklistValue.Standard.snippetType.Image" source="Image">Image</String>
	<String id="PicklistValue.Standard.snippetType.Link" source="Link">Link</String>
	<String id="PicklistValue.Standard.snippetType.Text" source="Text">Text</String>
	<String id="PicklistValue.Standard.orderStatus.Activated" source="Activated">Activated</String>
	<String id="PicklistValue.Standard.orderStatus.Draft" source="Draft">Draft</String>
	<String id="PicklistValue.Standard.orgMetricCategory.Custom Code" source="Custom Code">Custom Code</String>
	<String id="PicklistValue.Standard.orgMetricCategory.Custom Layouts" source="Custom Layouts">Custom Layouts</String>
	<String id="PicklistValue.Standard.orgMetricCategory.Fields" source="Fields">Fields</String>
	<String id="PicklistValue.Standard.orgMetricCategory.Improve Org Security" source="Improve Org Security">Improve Org Security</String>
	<String id="PicklistValue.Standard.orgMetricCategory.Improve User Experience" source="Improve User Experience">Improve User Experience</String>
	<String id="PicklistValue.Standard.orgMetricCategory.Increase User Adoption" source="Increase User Adoption">Increase User Adoption</String>
	<String id="PicklistValue.Standard.orgMetricCategory.Object Limits" source="Object Limits">Object Limits</String>
	<String id="PicklistValue.Standard.orgMetricCategory.Org Limits" source="Org Limits">Org Limits</String>
	<String id="PicklistValue.Standard.orgMetricCategory.Reports And Dashboards" source="Reports And Dashboards">Reports And Dashboards</String>
	<String id="PicklistValue.Standard.orgMetricCategory.Usage" source="Usage">Usage</String>
	<String id="PicklistValue.Standard.orgMetricCategory.User Management" source="User Management">User Management</String>
	<String id="PicklistValue.Standard.orgMetricCategory.Workflow" source="Workflow">Workflow</String>
	<String id="PicklistValue.Standard.orgMetricType.API Versions" source="API Versions">API Versions</String>
	<String id="PicklistValue.Standard.orgMetricType.Active Sharing Rule Limits" source="Active Sharing Rule Limits">Active Sharing Rule Limits</String>
	<String id="PicklistValue.Standard.orgMetricType.Active Validation Rule Limits" source="Active Validation Rule Limits">Active Validation Rule Limits</String>
	<String id="PicklistValue.Standard.orgMetricType.Active Workflow Rule Limits" source="Active Workflow Rule Limits">Active Workflow Rule Limits</String>
	<String id="PicklistValue.Standard.orgMetricType.Case Feed" source="Case Feed">Case Feed</String>
	<String id="PicklistValue.Standard.orgMetricType.Convert Attachment to Files" source="Convert Attachment to Files">Convert Attachment to Files</String>
	<String id="PicklistValue.Standard.orgMetricType.Critical Permission Assignments" source="Critical Permission Assignments">Critical Permission Assignments</String>
	<String id="PicklistValue.Standard.orgMetricType.Custom Field Limits" source="Custom Field Limits">Custom Field Limits</String>
	<String id="PicklistValue.Standard.orgMetricType.Custom Profiles with a Low Number of Users" source="Custom Profiles with a Low Number of Users">Custom Profiles with a Low Number of Users</String>
	<String id="PicklistValue.Standard.orgMetricType.Data Storage Limits" source="Data Storage Limits">Data Storage Limits</String>
	<String id="PicklistValue.Standard.orgMetricType.Details Tab on Record Pages" source="Details Tab on Record Pages">Details Tab on Record Pages</String>
	<String id="PicklistValue.Standard.orgMetricType.Disable Debug Mode" source="Disable Debug Mode">Disable Debug Mode</String>
	<String id="PicklistValue.Standard.orgMetricType.Duplicate Management" source="Duplicate Management">Duplicate Management</String>
	<String id="PicklistValue.Standard.orgMetricType.Field Usage" source="Field Usage">Field Usage</String>
	<String id="PicklistValue.Standard.orgMetricType.Fields on Page Layouts" source="Fields on Page Layouts">Fields on Page Layouts</String>
	<String id="PicklistValue.Standard.orgMetricType.File Storage Limits" source="File Storage Limits">File Storage Limits</String>
	<String id="PicklistValue.Standard.orgMetricType.Files Adoption" source="Files Adoption">Files Adoption</String>
	<String id="PicklistValue.Standard.orgMetricType.Formula Fields with JavaScript Code" source="Formula Fields with JavaScript Code">Formula Fields with JavaScript Code</String>
	<String id="PicklistValue.Standard.orgMetricType.Hard-Coded URLs" source="Hard-Coded URLs">Hard-Coded URLs</String>
	<String id="PicklistValue.Standard.orgMetricType.Inactive Chatter Users" source="Inactive Chatter Users">Inactive Chatter Users</String>
	<String id="PicklistValue.Standard.orgMetricType.Inactive Validation Rules" source="Inactive Validation Rules">Inactive Validation Rules</String>
	<String id="PicklistValue.Standard.orgMetricType.Inactive Workflow Rules" source="Inactive Workflow Rules">Inactive Workflow Rules</String>
	<String id="PicklistValue.Standard.orgMetricType.Incomplete Chatter Profiles" source="Incomplete Chatter Profiles">Incomplete Chatter Profiles</String>
	<String id="PicklistValue.Standard.orgMetricType.Keyboard Shortcuts" source="Keyboard Shortcuts">Keyboard Shortcuts</String>
	<String id="PicklistValue.Standard.orgMetricType.Lightning Components on Record Lightning Pages" source="Lightning Components on Record Lightning Pages">Lightning Components on Record Lightning Pages</String>
	<String id="PicklistValue.Standard.orgMetricType.Lightning Sales Console" source="Lightning Sales Console">Lightning Sales Console</String>
	<String id="PicklistValue.Standard.orgMetricType.Lightning Service Console" source="Lightning Service Console">Lightning Service Console</String>
	<String id="PicklistValue.Standard.orgMetricType.Macros" source="Macros">Macros</String>
	<String id="PicklistValue.Standard.orgMetricType.Migrating Workflow Rules to Flow Builder" source="Migrating Workflow Rules to Flow Builder">Migrating Workflow Rules to Flow Builder</String>
	<String id="PicklistValue.Standard.orgMetricType.Multiple Apex Triggers per Object" source="Multiple Apex Triggers per Object">Multiple Apex Triggers per Object</String>
	<String id="PicklistValue.Standard.orgMetricType.New Code Using Old API Versions" source="New Code Using Old API Versions">New Code Using Old API Versions</String>
	<String id="PicklistValue.Standard.orgMetricType.News and Twitter" source="News and Twitter">News and Twitter</String>
	<String id="PicklistValue.Standard.orgMetricType.Notes and Attachments Related List" source="Notes and Attachments Related List">Notes and Attachments Related List</String>
	<String id="PicklistValue.Standard.orgMetricType.Omni-Channel" source="Omni-Channel">Omni-Channel</String>
	<String id="PicklistValue.Standard.orgMetricType.Out-of-Date Browsers" source="Out-of-Date Browsers">Out-of-Date Browsers</String>
	<String id="PicklistValue.Standard.orgMetricType.Page Layouts per Object" source="Page Layouts per Object">Page Layouts per Object</String>
	<String id="PicklistValue.Standard.orgMetricType.Path" source="Path">Path</String>
	<String id="PicklistValue.Standard.orgMetricType.Permission Sets with a Low Number of Users" source="Permission Sets with a Low Number of Users">Permission Sets with a Low Number of Users</String>
	<String id="PicklistValue.Standard.orgMetricType.Record Types per Object" source="Record Types per Object">Record Types per Object</String>
	<String id="PicklistValue.Standard.orgMetricType.Replacing Related Lists with the Related List Quick Links Component" source="Replacing Related Lists with the Related List Quick Links Component">Replacing Related Lists with the Related List Quick Links Component</String>
	<String id="PicklistValue.Standard.orgMetricType.S-Controls" source="S-Controls">S-Controls</String>
	<String id="PicklistValue.Standard.orgMetricType.Static Resource Limits" source="Static Resource Limits">Static Resource Limits</String>
	<String id="PicklistValue.Standard.orgMetricType.Unassigned Custom Profiles" source="Unassigned Custom Profiles">Unassigned Custom Profiles</String>
	<String id="PicklistValue.Standard.orgMetricType.Unassigned Page Layouts" source="Unassigned Page Layouts">Unassigned Page Layouts</String>
	<String id="PicklistValue.Standard.orgMetricType.Unassigned Permission Sets" source="Unassigned Permission Sets">Unassigned Permission Sets</String>
	<String id="PicklistValue.Standard.orgMetricType.Unassigned Record Types" source="Unassigned Record Types">Unassigned Record Types</String>
	<String id="PicklistValue.Standard.orgMetricType.Unassigned Roles" source="Unassigned Roles">Unassigned Roles</String>
	<String id="PicklistValue.Standard.orgMetricType.Unsupported Browsers" source="Unsupported Browsers">Unsupported Browsers</String>
	<String id="PicklistValue.Standard.orgMetricType.Unused Dashboards" source="Unused Dashboards">Unused Dashboards</String>
	<String id="PicklistValue.Standard.orgMetricType.Unused Reports" source="Unused Reports">Unused Reports</String>
	<String id="PicklistValue.Standard.orgMetricType.User Logins" source="User Logins">User Logins</String>
	<String id="PicklistValue.Standard.orgMetricStatus.Action Required" source="Action Required">Action Required</String>
	<String id="PicklistValue.Standard.orgMetricStatus.Immediate Action Required" source="Immediate Action Required">Immediate Action Required</String>
	<String id="PicklistValue.Standard.orgMetricStatus.No Action Required" source="No Action Required">No Action Required</String>
	<String id="PicklistValue.Standard.orgMetricStatus.Not Currently Enabled" source="Not Currently Enabled">Not Currently Enabled</String>
	<String id="PicklistValue.Standard.orgMetricStatus.Review Required" source="Review Required">Review Required</String>
	<String id="PicklistValue.Standard.orgMetricStatus.Unable to Analyze" source="Unable to Analyze">Unable to Analyze</String>
	<String id="PicklistValue.Standard.orgMetricImplEffort.1 - 2 hours" source="1 - 2 hours">1 - 2 hours</String>
	<String id="PicklistValue.Standard.orgMetricImplEffort.30 - 60 minutes" source="30 - 60 minutes">30 - 60 minutes</String>
	<String id="PicklistValue.Standard.orgMetricImplEffort.< 30 minutes" source="< 30 minutes">< 30 minutes</String>
	<String id="PicklistValue.Standard.orgMetricImplEffort.> 2 hours" source="> 2 hours">> 2 hours</String>
	<String id="PicklistValue.Standard.campaignMemberStatus.Planned" source="Planned">Planned</String>
	<String id="PicklistValue.Standard.campaignMemberStatus.Received" source="Received">Received</String>
	<String id="PicklistValue.Standard.campaignMemberStatus.Responded" source="Responded">Responded</String>
	<String id="PicklistValue.Standard.campaignMemberStatus.Sent" source="Sent">Sent</String>
	<String id="PicklistValue.Standard.product2Family.None" source="None">None</String>
	<String id="PicklistValue.Standard.complianceGroup.CCPA" source="CCPA">CCPA</String>
	<String id="PicklistValue.Standard.complianceGroup.COPPA" source="COPPA">COPPA</String>
	<String id="PicklistValue.Standard.complianceGroup.GDPR" source="GDPR">GDPR</String>
	<String id="PicklistValue.Standard.complianceGroup.HIPAA" source="HIPAA">HIPAA</String>
	<String id="PicklistValue.Standard.complianceGroup.PCI" source="PCI">PCI</String>
	<String id="PicklistValue.Standard.complianceGroup.PII" source="PII">PII</String>
	<String id="PicklistValue.Standard.contactPointAddressType.Billing" source="Billing">Billing</String>
	<String id="PicklistValue.Standard.contactPointAddressType.Shipping" source="Shipping">Shipping</String>
	<String id="PicklistValue.Standard.orderItemSummaryChgRsn.Unknown" source="Unknown">Unknown</String>
	<String id="PicklistValue.Standard.orderSummaryRoutingSchdRsn.Unknown" source="Unknown">Unknown</String>
	<String id="PicklistValue.Standard.accountContactRole.Business User" source="Business User">Business User</String>
	<String id="PicklistValue.Standard.accountContactRole.Decision Maker" source="Decision Maker">Decision Maker</String>
	<String id="PicklistValue.Standard.accountContactRole.Economic Buyer" source="Economic Buyer">Economic Buyer</String>
	<String id="PicklistValue.Standard.accountContactRole.Economic Decision Maker" source="Economic Decision Maker">Economic Decision Maker</String>
	<String id="PicklistValue.Standard.accountContactRole.Evaluator" source="Evaluator">Evaluator</String>
	<String id="PicklistValue.Standard.accountContactRole.Executive Sponsor" source="Executive Sponsor">Executive Sponsor</String>
	<String id="PicklistValue.Standard.accountContactRole.Influencer" source="Influencer">Influencer</String>
	<String id="PicklistValue.Standard.accountContactRole.Other" source="Other">Other</String>
	<String id="PicklistValue.Standard.accountContactRole.Technical Buyer" source="Technical Buyer">Technical Buyer</String>
	<String id="PicklistValue.Standard.orderSummaryStatus.Created" source="Created">Created</String>
	<String id="PicklistValue.Standard.contractContactRole.Business User" source="Business User">Business User</String>
	<String id="PicklistValue.Standard.contractContactRole.Decision Maker" source="Decision Maker">Decision Maker</String>
	<String id="PicklistValue.Standard.contractContactRole.Economic Buyer" source="Economic Buyer">Economic Buyer</String>
	<String id="PicklistValue.Standard.contractContactRole.Economic Decision Maker" source="Economic Decision Maker">Economic Decision Maker</String>
	<String id="PicklistValue.Standard.contractContactRole.Evaluator" source="Evaluator">Evaluator</String>
	<String id="PicklistValue.Standard.contractContactRole.Executive Sponsor" source="Executive Sponsor">Executive Sponsor</String>
	<String id="PicklistValue.Standard.contractContactRole.Influencer" source="Influencer">Influencer</String>
	<String id="PicklistValue.Standard.contractContactRole.Other" source="Other">Other</String>
	<String id="PicklistValue.Standard.contractContactRole.Technical Buyer" source="Technical Buyer">Technical Buyer</String>
	<String id="PicklistValue.Standard.cardType.American Express" source="American Express">American Express</String>
	<String id="PicklistValue.Standard.cardType.Diners Club" source="Diners Club">Diners Club</String>
	<String id="PicklistValue.Standard.cardType.JCB" source="JCB">JCB</String>
	<String id="PicklistValue.Standard.cardType.Maestro" source="Maestro">Maestro</String>
	<String id="PicklistValue.Standard.cardType.Master Card" source="Master Card">Master Card</String>
	<String id="PicklistValue.Standard.cardType.Visa" source="Visa">Visa</String>
	<String id="PicklistValue.Standard.callResolution.Resolved" source="Resolved">Resolved</String>
	<String id="PicklistValue.Standard.industry.Agriculture" source="Agriculture">Agriculture</String>
	<String id="PicklistValue.Standard.industry.Apparel" source="Apparel">Apparel</String>
	<String id="PicklistValue.Standard.industry.Banking" source="Banking">Banking</String>
	<String id="PicklistValue.Standard.industry.Biotechnology" source="Biotechnology">Biotechnology</String>
	<String id="PicklistValue.Standard.industry.Chemicals" source="Chemicals">Chemicals</String>
	<String id="PicklistValue.Standard.industry.Communications" source="Communications">Communications</String>
	<String id="PicklistValue.Standard.industry.Construction" source="Construction">Construction</String>
	<String id="PicklistValue.Standard.industry.Consulting" source="Consulting">Consulting</String>
	<String id="PicklistValue.Standard.industry.Education" source="Education">Education</String>
	<String id="PicklistValue.Standard.industry.Electronics" source="Electronics">Electronics</String>
	<String id="PicklistValue.Standard.industry.Energy" source="Energy">Energy</String>
	<String id="PicklistValue.Standard.industry.Engineering" source="Engineering">Engineering</String>
	<String id="PicklistValue.Standard.industry.Entertainment" source="Entertainment">Entertainment</String>
	<String id="PicklistValue.Standard.industry.Environmental" source="Environmental">Environmental</String>
	<String id="PicklistValue.Standard.industry.Finance" source="Finance">Finance</String>
	<String id="PicklistValue.Standard.industry.Food & Beverage" source="Food & Beverage">Food & Beverage</String>
	<String id="PicklistValue.Standard.industry.Government" source="Government">Government</String>
	<String id="PicklistValue.Standard.industry.Healthcare" source="Healthcare">Healthcare</String>
	<String id="PicklistValue.Standard.industry.Hospitality" source="Hospitality">Hospitality</String>
	<String id="PicklistValue.Standard.industry.Insurance" source="Insurance">Insurance</String>
	<String id="PicklistValue.Standard.industry.Machinery" source="Machinery">Machinery</String>
	<String id="PicklistValue.Standard.industry.Manufacturing" source="Manufacturing">Manufacturing</String>
	<String id="PicklistValue.Standard.industry.Media" source="Media">Media</String>
	<String id="PicklistValue.Standard.industry.Not For Profit" source="Not For Profit">Not For Profit</String>
	<String id="PicklistValue.Standard.industry.Other" source="Other">Other</String>
	<String id="PicklistValue.Standard.industry.Recreation" source="Recreation">Recreation</String>
	<String id="PicklistValue.Standard.industry.Retail" source="Retail">Retail</String>
	<String id="PicklistValue.Standard.industry.Shipping" source="Shipping">Shipping</String>
	<String id="PicklistValue.Standard.industry.Technology" source="Technology">Technology</String>
	<String id="PicklistValue.Standard.industry.Telecommunications" source="Telecommunications">Telecommunications</String>
	<String id="PicklistValue.Standard.industry.Transportation" source="Transportation">Transportation</String>
	<String id="PicklistValue.Standard.industry.Utilities" source="Utilities">Utilities</String>
	<String id="PicklistValue.Standard.assetStatus.Installed" source="Installed">Installed</String>
	<String id="PicklistValue.Standard.assetStatus.Obsolete" source="Obsolete">Obsolete</String>
	<String id="PicklistValue.Standard.assetStatus.Purchased" source="Purchased">Purchased</String>
	<String id="PicklistValue.Standard.assetStatus.Registered" source="Registered">Registered</String>
	<String id="PicklistValue.Standard.assetStatus.Shipped" source="Shipped">Shipped</String>
	<String id="PicklistValue.Standard.fiscalYearQuarterPrefix.FQ" source="FQ">FQ</String>
	<String id="PicklistValue.Standard.fiscalYearQuarterPrefix.Q" source="Q">Q</String>
	<String id="PicklistValue.Standard.fiscalYearQuarterPrefix.Quarter" source="Quarter">Quarter</String>
	<String id="PicklistValue.Standard.fiscalYearQuarterPrefix.Trimester" source="Trimester">Trimester</String>
	<String id="PicklistValue.Standard.assetActionCategory.Cancellations" source="Cancellations">Cancellations</String>
	<String id="PicklistValue.Standard.assetActionCategory.Cross-Sells" source="Cross-Sells">Cross-Sells</String>
	<String id="PicklistValue.Standard.assetActionCategory.Downsells" source="Downsells">Downsells</String>
	<String id="PicklistValue.Standard.assetActionCategory.Initial Sale" source="Initial Sale">Initial Sale</String>
	<String id="PicklistValue.Standard.assetActionCategory.Other" source="Other">Other</String>
	<String id="PicklistValue.Standard.assetActionCategory.Renewals" source="Renewals">Renewals</String>
	<String id="PicklistValue.Standard.assetActionCategory.Terms And Conditions Changes" source="Terms And Conditions Changes">Terms And Conditions Changes</String>
	<String id="PicklistValue.Standard.assetActionCategory.Transfers" source="Transfers">Transfers</String>
	<String id="PicklistValue.Standard.assetActionCategory.Upsells" source="Upsells">Upsells</String>
	<String id="PicklistValue.Standard.digitalAssetStatus.Error" source="Error">Error</String>
	<String id="PicklistValue.Standard.digitalAssetStatus.Off" source="Off">Off</String>
	<String id="PicklistValue.Standard.digitalAssetStatus.On" source="On">On</String>
	<String id="PicklistValue.Standard.digitalAssetStatus.Warning" source="Warning">Warning</String>
	<String id="PicklistValue.Standard.fiscalYearPeriodPrefix.FP" source="FP">FP</String>
	<String id="PicklistValue.Standard.fiscalYearPeriodPrefix.Month" source="Month">Month</String>
	<String id="PicklistValue.Standard.fiscalYearPeriodPrefix.P" source="P">P</String>
	<String id="PicklistValue.Standard.fiscalYearPeriodPrefix.Period" source="Period">Period</String>
	<String id="PicklistValue.Standard.statusReason.Not Ready" source="Not Ready">Not Ready</String>
	<String id="PicklistValue.Standard.statusReason.Off" source="Off">Off</String>
	<String id="PicklistValue.Standard.statusReason.Offline" source="Offline">Offline</String>
	<String id="PicklistValue.Standard.statusReason.Online" source="Online">Online</String>
	<String id="PicklistValue.Standard.statusReason.Paused" source="Paused">Paused</String>
	<String id="PicklistValue.Standard.statusReason.Standby" source="Standby">Standby</String>
	<String id="PicklistValue.Standard.fiscalYearQuarterName.Fall" source="Fall">Fall</String>
	<String id="PicklistValue.Standard.fiscalYearQuarterName.Spring" source="Spring">Spring</String>
	<String id="PicklistValue.Standard.fiscalYearQuarterName.Summer" source="Summer">Summer</String>
	<String id="PicklistValue.Standard.fiscalYearQuarterName.Winter" source="Winter">Winter</String>
	<String id="PicklistValue.Standard.workStepStatus.Completed" source="Completed">Completed</String>
	<String id="PicklistValue.Standard.workStepStatus.In Progress" source="In Progress">In Progress</String>
	<String id="PicklistValue.Standard.workStepStatus.New" source="New">New</String>
	<String id="PicklistValue.Standard.workStepStatus.Not Applicable" source="Not Applicable">Not Applicable</String>
	<String id="PicklistValue.Standard.workStepStatus.Paused" source="Paused">Paused</String>
	<String id="PicklistValue.Standard.caseContactRole.Business Contact" source="Business Contact">Business Contact</String>
	<String id="PicklistValue.Standard.caseContactRole.Decision Maker" source="Decision Maker">Decision Maker</String>
	<String id="PicklistValue.Standard.caseContactRole.Other" source="Other">Other</String>
	<String id="PicklistValue.Standard.caseContactRole.Technical Contact" source="Technical Contact">Technical Contact</String>
	<String id="PicklistValue.Standard.finTrxReferenceEntityType.Credit memo" source="Credit memo">Credit memo</String>
	<String id="PicklistValue.Standard.finTrxReferenceEntityType.Credit memo line" source="Credit memo line">Credit memo line</String>
	<String id="PicklistValue.Standard.finTrxReferenceEntityType.Credit memo line invoice application" source="Credit memo line invoice application">Credit memo line invoice application</String>
	<String id="PicklistValue.Standard.finTrxReferenceEntityType.Credit memo line invoice line application" source="Credit memo line invoice line application">Credit memo line invoice line application</String>
	<String id="PicklistValue.Standard.finTrxReferenceEntityType.Credit memo line tax" source="Credit memo line tax">Credit memo line tax</String>
	<String id="PicklistValue.Standard.finTrxReferenceEntityType.Debit memo" source="Debit memo">Debit memo</String>
	<String id="PicklistValue.Standard.finTrxReferenceEntityType.Debit memo line" source="Debit memo line">Debit memo line</String>
	<String id="PicklistValue.Standard.finTrxReferenceEntityType.Debit memo line credit memo application" source="Debit memo line credit memo application">Debit memo line credit memo application</String>
	<String id="PicklistValue.Standard.finTrxReferenceEntityType.Debit memo line credit memo line application" source="Debit memo line credit memo line application">Debit memo line credit memo line application</String>
	<String id="PicklistValue.Standard.finTrxReferenceEntityType.Debit memo line invoice application" source="Debit memo line invoice application">Debit memo line invoice application</String>
	<String id="PicklistValue.Standard.finTrxReferenceEntityType.Debit memo line invoice line application" source="Debit memo line invoice line application">Debit memo line invoice line application</String>
	<String id="PicklistValue.Standard.finTrxReferenceEntityType.Debit memo line tax" source="Debit memo line tax">Debit memo line tax</String>
	<String id="PicklistValue.Standard.finTrxReferenceEntityType.Invoice" source="Invoice">Invoice</String>
	<String id="PicklistValue.Standard.finTrxReferenceEntityType.Invoice line" source="Invoice line">Invoice line</String>
	<String id="PicklistValue.Standard.finTrxReferenceEntityType.Invoice line tax" source="Invoice line tax">Invoice line tax</String>
	<String id="PicklistValue.Standard.finTrxReferenceEntityType.Other" source="Other">Other</String>
	<String id="PicklistValue.Standard.finTrxReferenceEntityType.Payment" source="Payment">Payment</String>
	<String id="PicklistValue.Standard.finTrxReferenceEntityType.Payment debit memo application" source="Payment debit memo application">Payment debit memo application</String>
	<String id="PicklistValue.Standard.finTrxReferenceEntityType.Payment debit memo line application" source="Payment debit memo line application">Payment debit memo line application</String>
	<String id="PicklistValue.Standard.finTrxReferenceEntityType.Payment invoice application" source="Payment invoice application">Payment invoice application</String>
	<String id="PicklistValue.Standard.finTrxReferenceEntityType.Payment invoice line application" source="Payment invoice line application">Payment invoice line application</String>
	<String id="PicklistValue.Standard.finTrxReferenceEntityType.Refund" source="Refund">Refund</String>
	<String id="PicklistValue.Standard.finTrxReferenceEntityType.Refund credit memo application" source="Refund credit memo application">Refund credit memo application</String>
	<String id="PicklistValue.Standard.finTrxReferenceEntityType.Refund credit memo line application" source="Refund credit memo line application">Refund credit memo line application</String>
	<String id="PicklistValue.Standard.finTrxReferenceEntityType.Refund payment application" source="Refund payment application">Refund payment application</String>
	<String id="PicklistValue.Standard.finTrxReferenceEntityType.Sub invoice line" source="Sub invoice line">Sub invoice line</String>
	<String id="PicklistValue.Standard.finTrxReferenceEntityType.Sub invoice line tax" source="Sub invoice line tax">Sub invoice line tax</String>
	<String id="PicklistValue.Standard.financeEventType.Allocated" source="Allocated">Allocated</String>
	<String id="PicklistValue.Standard.financeEventType.Canceled" source="Canceled">Canceled</String>
	<String id="PicklistValue.Standard.financeEventType.Changed" source="Changed">Changed</String>
	<String id="PicklistValue.Standard.financeEventType.Other" source="Other">Other</String>
	<String id="PicklistValue.Standard.financeEventType.Posted" source="Posted">Posted</String>
	<String id="PicklistValue.Standard.financeEventType.Unallocated" source="Unallocated">Unallocated</String>
	<String id="PicklistValue.Standard.financeEventType.Void" source="Void">Void</String>
	<String id="PicklistValue.Standard.financeEventAction.Cancel & rebill" source="Cancel & rebill">Cancel & rebill</String>
	<String id="PicklistValue.Standard.financeEventAction.Convert negative invoice lines" source="Convert negative invoice lines">Convert negative invoice lines</String>
	<String id="PicklistValue.Standard.financeEventAction.Credit invoice header" source="Credit invoice header">Credit invoice header</String>
	<String id="PicklistValue.Standard.financeEventAction.Credit invoice line" source="Credit invoice line">Credit invoice line</String>
	<String id="PicklistValue.Standard.financeEventAction.Currency change on sub invoice line" source="Currency change on sub invoice line">Currency change on sub invoice line</String>
	<String id="PicklistValue.Standard.financeEventAction.Debit credit memo header" source="Debit credit memo header">Debit credit memo header</String>
	<String id="PicklistValue.Standard.financeEventAction.Debit credit memo line" source="Debit credit memo line">Debit credit memo line</String>
	<String id="PicklistValue.Standard.financeEventAction.Debit invoice header" source="Debit invoice header">Debit invoice header</String>
	<String id="PicklistValue.Standard.financeEventAction.Debit invoice line" source="Debit invoice line">Debit invoice line</String>
	<String id="PicklistValue.Standard.financeEventAction.Invoice line reference changed on sub invoice line" source="Invoice line reference changed on sub invoice line">Invoice line reference changed on sub invoice line</String>
	<String id="PicklistValue.Standard.financeEventAction.Issue a standalone credit" source="Issue a standalone credit">Issue a standalone credit</String>
	<String id="PicklistValue.Standard.financeEventAction.Issue a standalone debit" source="Issue a standalone debit">Issue a standalone debit</String>
	<String id="PicklistValue.Standard.financeEventAction.Issue a standalone refund" source="Issue a standalone refund">Issue a standalone refund</String>
	<String id="PicklistValue.Standard.financeEventAction.Other" source="Other">Other</String>
	<String id="PicklistValue.Standard.financeEventAction.Pay debit memo header" source="Pay debit memo header">Pay debit memo header</String>
	<String id="PicklistValue.Standard.financeEventAction.Pay debit memo line" source="Pay debit memo line">Pay debit memo line</String>
	<String id="PicklistValue.Standard.financeEventAction.Pay invoice header" source="Pay invoice header">Pay invoice header</String>
	<String id="PicklistValue.Standard.financeEventAction.Pay invoice line" source="Pay invoice line">Pay invoice line</String>
	<String id="PicklistValue.Standard.financeEventAction.Post a standalone payment" source="Post a standalone payment">Post a standalone payment</String>
	<String id="PicklistValue.Standard.financeEventAction.Post an invoice" source="Post an invoice">Post an invoice</String>
	<String id="PicklistValue.Standard.financeEventAction.Refund a credit memo header" source="Refund a credit memo header">Refund a credit memo header</String>
	<String id="PicklistValue.Standard.financeEventAction.Refund a credit memo line" source="Refund a credit memo line">Refund a credit memo line</String>
	<String id="PicklistValue.Standard.financeEventAction.Refund a payment" source="Refund a payment">Refund a payment</String>
	<String id="PicklistValue.Standard.financeEventAction.Subtotal change on sub invoice line" source="Subtotal change on sub invoice line">Subtotal change on sub invoice line</String>
	<String id="PicklistValue.Standard.financeEventAction.Tax change on sub invoice line" source="Tax change on sub invoice line">Tax change on sub invoice line</String>
	<String id="PicklistValue.Standard.financeEventAction.Unallocate credit from invoice header" source="Unallocate credit from invoice header">Unallocate credit from invoice header</String>
	<String id="PicklistValue.Standard.financeEventAction.Unallocate credit from invoice line" source="Unallocate credit from invoice line">Unallocate credit from invoice line</String>
	<String id="PicklistValue.Standard.financeEventAction.Unallocate debit from credit memo header" source="Unallocate debit from credit memo header">Unallocate debit from credit memo header</String>
	<String id="PicklistValue.Standard.financeEventAction.Unallocate debit from credit memo line" source="Unallocate debit from credit memo line">Unallocate debit from credit memo line</String>
	<String id="PicklistValue.Standard.financeEventAction.Unallocate debit from invoice header" source="Unallocate debit from invoice header">Unallocate debit from invoice header</String>
	<String id="PicklistValue.Standard.financeEventAction.Unallocate debit from invoice line" source="Unallocate debit from invoice line">Unallocate debit from invoice line</String>
	<String id="PicklistValue.Standard.financeEventAction.Unallocate payment from debit line" source="Unallocate payment from debit line">Unallocate payment from debit line</String>
	<String id="PicklistValue.Standard.financeEventAction.Unallocate payment from debit memo header" source="Unallocate payment from debit memo header">Unallocate payment from debit memo header</String>
	<String id="PicklistValue.Standard.financeEventAction.Unallocate payment from invoice header" source="Unallocate payment from invoice header">Unallocate payment from invoice header</String>
	<String id="PicklistValue.Standard.financeEventAction.Unallocate payment from invoice line" source="Unallocate payment from invoice line">Unallocate payment from invoice line</String>
	<String id="PicklistValue.Standard.financeEventAction.Unallocate refund from credit memo header" source="Unallocate refund from credit memo header">Unallocate refund from credit memo header</String>
	<String id="PicklistValue.Standard.financeEventAction.Unallocate refund from credit memo line" source="Unallocate refund from credit memo line">Unallocate refund from credit memo line</String>
	<String id="PicklistValue.Standard.financeEventAction.Unallocate refund from payment" source="Unallocate refund from payment">Unallocate refund from payment</String>
	<String id="PicklistValue.Standard.financeEventAction.Void a standalone credit" source="Void a standalone credit">Void a standalone credit</String>
	<String id="PicklistValue.Standard.financeEventAction.Void a standalone debit" source="Void a standalone debit">Void a standalone debit</String>
	<String id="PicklistValue.Standard.financeEventAction.Void a standalone payment" source="Void a standalone payment">Void a standalone payment</String>
	<String id="PicklistValue.Standard.financeEventAction.Void a standalone refund" source="Void a standalone refund">Void a standalone refund</String>
	<String id="PicklistValue.Standard.financeEventAction.Void an invoice" source="Void an invoice">Void an invoice</String>
	<String id="PicklistValue.Standard.processExceptionStatus.Ignored" source="Ignored">Ignored</String>
	<String id="PicklistValue.Standard.processExceptionStatus.New" source="New">New</String>
	<String id="PicklistValue.Standard.processExceptionStatus.Paused" source="Paused">Paused</String>
	<String id="PicklistValue.Standard.processExceptionStatus.Resolved" source="Resolved">Resolved</String>
	<String id="PicklistValue.Standard.processExceptionStatus.Triaged" source="Triaged">Triaged</String>
	<String id="PicklistValue.Standard.processExceptionStatus.Voided" source="Voided">Voided</String>
	<String id="PicklistValue.Standard.processExceptionCategory.Fulfillment" source="Fulfillment">Fulfillment</String>
	<String id="PicklistValue.Standard.processExceptionCategory.Invoicing" source="Invoicing">Invoicing</String>
	<String id="PicklistValue.Standard.processExceptionCategory.Order Activation" source="Order Activation">Order Activation</String>
	<String id="PicklistValue.Standard.processExceptionCategory.Order Approval" source="Order Approval">Order Approval</String>
	<String id="PicklistValue.Standard.processExceptionCategory.Payment" source="Payment">Payment</String>
	<String id="PicklistValue.Standard.forecastCategoryName.Best Case" source="Best Case">Best Case</String>
	<String id="PicklistValue.Standard.forecastCategoryName.Closed" source="Closed">Closed</String>
	<String id="PicklistValue.Standard.forecastCategoryName.Commit" source="Commit">Commit</String>
	<String id="PicklistValue.Standard.forecastCategoryName.Omitted" source="Omitted">Omitted</String>
	<String id="PicklistValue.Standard.forecastCategoryName.Pipeline" source="Pipeline">Pipeline</String>
	<String id="PicklistValue.Standard.processExceptionSeverity.High" source="High">High</String>
	<String id="PicklistValue.Standard.processExceptionSeverity.Low" source="Low">Low</String>
	<String id="PicklistValue.Standard.processExceptionPriority.High" source="High">High</String>
	<String id="PicklistValue.Standard.processExceptionPriority.Low" source="Low">Low</String>
	<String id="PicklistValue.Standard.exceptionType.OM Apply Failed" source="OM Apply Failed">OM Apply Failed</String>
	<String id="PicklistValue.Standard.exceptionType.OM Capture Failed" source="OM Capture Failed">OM Capture Failed</String>
	<String id="PicklistValue.Standard.exceptionType.OM Refund Failed" source="OM Refund Failed">OM Refund Failed</String>
	<String id="PicklistValue.Standard.contactPointUsageType.Home" source="Home">Home</String>
	<String id="PicklistValue.Standard.contactPointUsageType.Inactive" source="Inactive">Inactive</String>
	<String id="PicklistValue.Standard.contactPointUsageType.Temporary" source="Temporary">Temporary</String>
	<String id="PicklistValue.Standard.contactPointUsageType.Work" source="Work">Work</String>
	<String id="PicklistValue.Standard.returnOrderLineItemReasonForRejection.Damaged Item" source="Damaged Item">Damaged Item</String>
	<String id="PicklistValue.Standard.returnOrderLineItemReasonForRejection.Expired Warranty" source="Expired Warranty">Expired Warranty</String>
	<String id="PicklistValue.Standard.returnOrderLineItemReasonForRejection.Missing Item or Part" source="Missing Item or Part">Missing Item or Part</String>
	<String id="PicklistValue.Standard.returnOrderLineItemReasonForRejection.Wrong Item" source="Wrong Item">Wrong Item</String>
	<String id="PicklistValue.Standard.eventSubject.Call" source="Call">Call</String>
	<String id="PicklistValue.Standard.eventSubject.Email" source="Email">Email</String>
	<String id="PicklistValue.Standard.eventSubject.Meeting" source="Meeting">Meeting</String>
	<String id="PicklistValue.Standard.eventSubject.Other" source="Other">Other</String>
	<String id="PicklistValue.Standard.eventSubject.Send Letter/Quote" source="Send Letter/Quote">Send Letter/Quote</String>
	<String id="PicklistValue.Standard.entitlementType.Phone Support" source="Phone Support">Phone Support</String>
	<String id="PicklistValue.Standard.entitlementType.Web Support" source="Web Support">Web Support</String>
	<String id="PicklistValue.Standard.serviceContractApprovalStatus.Activated" source="Activated">Activated</String>
	<String id="PicklistValue.Standard.serviceContractApprovalStatus.Draft" source="Draft">Draft</String>
	<String id="PicklistValue.Standard.serviceContractApprovalStatus.In Approval Process" source="In Approval Process">In Approval Process</String>
	<String id="PicklistValue.Standard.quickTextCategory.Closings" source="Closings">Closings</String>
	<String id="PicklistValue.Standard.quickTextCategory.FAQ" source="FAQ">FAQ</String>
	<String id="PicklistValue.Standard.quickTextCategory.Greetings" source="Greetings">Greetings</String>
	<String id="PicklistValue.Standard.taskPriority.High" source="High">High</String>
	<String id="PicklistValue.Standard.taskPriority.Low" source="Low">Low</String>
	<String id="PicklistValue.Standard.taskPriority.Normal" source="Normal">Normal</String>
	<String id="PicklistValue.Standard.quickTextChannel.Email" source="Email">Email</String>
	<String id="PicklistValue.Standard.quickTextChannel.Event" source="Event">Event</String>
	<String id="PicklistValue.Standard.quickTextChannel.Internal" source="Internal">Internal</String>
	<String id="PicklistValue.Standard.quickTextChannel.Phone" source="Phone">Phone</String>
	<String id="PicklistValue.Standard.quickTextChannel.Portal" source="Portal">Portal</String>
	<String id="PicklistValue.Standard.quickTextChannel.Task" source="Task">Task</String>
	<String id="PicklistValue.Standard.salesChannelType.B2B" source="B2B">B2B</String>
	<String id="PicklistValue.Standard.salesChannelType.B2C" source="B2C">B2C</String>
	<String id="PicklistValue.Standard.salesChannelType.Other" source="Other">Other</String>
	<String id="PicklistValue.Standard.problemStatus.Closed" source="Closed">Closed</String>
	<String id="PicklistValue.Standard.problemStatus.Fix In Progress" source="Fix In Progress">Fix In Progress</String>
	<String id="PicklistValue.Standard.problemStatus.Known Error" source="Known Error">Known Error</String>
	<String id="PicklistValue.Standard.problemStatus.New" source="New">New</String>
	<String id="PicklistValue.Standard.problemStatus.Open" source="Open">Open</String>
	<String id="PicklistValue.Standard.problemStatus.Pending Change" source="Pending Change">Pending Change</String>
	<String id="PicklistValue.Standard.problemStatus.Resolved" source="Resolved">Resolved</String>
	<String id="PicklistValue.Standard.problemStatus.Root Case Analysis" source="Root Case Analysis">Root Case Analysis</String>
	<String id="PicklistValue.Standard.problemStatus.Work In Progress" source="Work In Progress">Work In Progress</String>
	<String id="PicklistValue.Standard.problemImpact.High" source="High">High</String>
	<String id="PicklistValue.Standard.problemImpact.Low" source="Low">Low</String>
	<String id="PicklistValue.Standard.problemImpact.Medium" source="Medium">Medium</String>
	<String id="PicklistValue.Standard.problemUrgency.High" source="High">High</String>
	<String id="PicklistValue.Standard.problemUrgency.Low" source="Low">Low</String>
	<String id="PicklistValue.Standard.problemUrgency.Medium" source="Medium">Medium</String>
	<String id="PicklistValue.Standard.problemPriority.Critical" source="Critical">Critical</String>
	<String id="PicklistValue.Standard.problemPriority.High" source="High">High</String>
	<String id="PicklistValue.Standard.problemPriority.Low" source="Low">Low</String>
	<String id="PicklistValue.Standard.problemPriority.Moderate" source="Moderate">Moderate</String>
	<String id="PicklistValue.Standard.incidentStatus.Closed" source="Closed">Closed</String>
	<String id="PicklistValue.Standard.incidentStatus.Completed" source="Completed">Completed</String>
	<String id="PicklistValue.Standard.incidentStatus.In Progress" source="In Progress">In Progress</String>
	<String id="PicklistValue.Standard.incidentStatus.New" source="New">New</String>
	<String id="PicklistValue.Standard.incidentStatus.Open" source="Open">Open</String>
	<String id="PicklistValue.Standard.incidentStatus.Problem Created" source="Problem Created">Problem Created</String>
	<String id="PicklistValue.Standard.incidentStatus.Resolved" source="Resolved">Resolved</String>
	<String id="PicklistValue.Standard.socialPostEngagementLevel.Commented" source="Commented">Commented</String>
	<String id="PicklistValue.Standard.socialPostEngagementLevel.Resolved" source="Resolved">Resolved</String>
	<String id="PicklistValue.Standard.socialPostEngagementLevel.Reviewed" source="Reviewed">Reviewed</String>
	<String id="PicklistValue.Standard.socialPostEngagementLevel.Submitted" source="Submitted">Submitted</String>
	<String id="PicklistValue.Standard.incidentImpact.High" source="High">High</String>
	<String id="PicklistValue.Standard.incidentImpact.Low" source="Low">Low</String>
	<String id="PicklistValue.Standard.incidentImpact.Medium" source="Medium">Medium</String>
	<String id="PicklistValue.Standard.incidentUrgency.High" source="High">High</String>
	<String id="PicklistValue.Standard.incidentUrgency.Low" source="Low">Low</String>
	<String id="PicklistValue.Standard.incidentUrgency.Medium" source="Medium">Medium</String>
	<String id="PicklistValue.Standard.incidentPriority.Critical" source="Critical">Critical</String>
	<String id="PicklistValue.Standard.incidentPriority.High" source="High">High</String>
	<String id="PicklistValue.Standard.incidentPriority.Low" source="Low">Low</String>
	<String id="PicklistValue.Standard.incidentPriority.Moderate" source="Moderate">Moderate</String>
	<String id="PicklistValue.Standard.changeRequestStatus.Approved" source="Approved">Approved</String>
	<String id="PicklistValue.Standard.changeRequestStatus.Canceled" source="Canceled">Canceled</String>
	<String id="PicklistValue.Standard.changeRequestStatus.Closed" source="Closed">Closed</String>
	<String id="PicklistValue.Standard.changeRequestStatus.Implementing" source="Implementing">Implementing</String>
	<String id="PicklistValue.Standard.changeRequestStatus.New" source="New">New</String>
	<String id="PicklistValue.Standard.changeRequestStatus.Open" source="Open">Open</String>
	<String id="PicklistValue.Standard.changeRequestStatus.Planning" source="Planning">Planning</String>
	<String id="PicklistValue.Standard.changeRequestStatus.Rejected" source="Rejected">Rejected</String>
	<String id="PicklistValue.Standard.changeRequestStatus.Reviewed" source="Reviewed">Reviewed</String>
	<String id="PicklistValue.Standard.changeRequestStatus.Scheduled" source="Scheduled">Scheduled</String>
	<String id="PicklistValue.Standard.changeRequestPriority.Critical" source="Critical">Critical</String>
	<String id="PicklistValue.Standard.changeRequestPriority.High" source="High">High</String>
	<String id="PicklistValue.Standard.changeRequestPriority.Low" source="Low">Low</String>
	<String id="PicklistValue.Standard.changeRequestPriority.Moderate" source="Moderate">Moderate</String>
	<String id="PicklistValue.Standard.socialPostClassification.Customer Case" source="Customer Case">Customer Case</String>
	<String id="PicklistValue.Standard.socialPostClassification.Inquiry" source="Inquiry">Inquiry</String>
	<String id="PicklistValue.Standard.socialPostClassification.Lead" source="Lead">Lead</String>
	<String id="PicklistValue.Standard.socialPostClassification.Outreach" source="Outreach">Outreach</String>
	<String id="PicklistValue.Standard.socialPostClassification.Product Review" source="Product Review">Product Review</String>
	<String id="PicklistValue.Standard.changeRequestImpact.High" source="High">High</String>
	<String id="PicklistValue.Standard.changeRequestImpact.Low" source="Low">Low</String>
	<String id="PicklistValue.Standard.changeRequestImpact.Medium" source="Medium">Medium</String>
	<String id="PicklistValue.Standard.changeRequestRiskLevel.High" source="High">High</String>
	<String id="PicklistValue.Standard.changeRequestRiskLevel.Low" source="Low">Low</String>
	<String id="PicklistValue.Standard.changeRequestRiskLevel.Medium" source="Medium">Medium</String>
	<String id="PicklistValue.Standard.fulfillmentReshipReason.Damaged" source="Damaged">Damaged</String>
	<String id="PicklistValue.Standard.fulfillmentReshipReason.Lost" source="Lost">Lost</String>
	<String id="PicklistValue.Standard.fulfillmentReshipReason.Unknown" source="Unknown">Unknown</String>
	<String id="PicklistValue.Standard.fulfillmentReshipReason.Wrong Item" source="Wrong Item">Wrong Item</String>
	<String id="PicklistValue.Standard.changeRequestRelationType.Caused By" source="Caused By">Caused By</String>
	<String id="PicklistValue.Standard.changeRequestRelationType.Resolved By" source="Resolved By">Resolved By</String>
	<String id="PicklistValue.Standard.problemIncidentRelationType.Caused By" source="Caused By">Caused By</String>
	<String id="PicklistValue.Standard.problemIncidentRelationType.Similar" source="Similar">Similar</String>
	<String id="PicklistValue.Standard.caseRelationType.Root Cause" source="Root Cause">Root Cause</String>
	<String id="PicklistValue.Standard.caseRelationType.Similar" source="Similar">Similar</String>
	<String id="PicklistValue.Standard.consequenceOfFailure.Critical" source="Critical">Critical</String>
	<String id="PicklistValue.Standard.consequenceOfFailure.Insignificant" source="Insignificant">Insignificant</String>
	<String id="PicklistValue.Standard.consequenceOfFailure.Major" source="Major">Major</String>
	<String id="PicklistValue.Standard.consequenceOfFailure.Minor" source="Minor">Minor</String>
	<String id="PicklistValue.Standard.consequenceOfFailure.Moderate" source="Moderate">Moderate</String>
	<String id="PicklistValue.Standard.taskSubject.Call" source="Call">Call</String>
	<String id="PicklistValue.Standard.taskSubject.Email" source="Email">Email</String>
	<String id="PicklistValue.Standard.taskSubject.Other" source="Other">Other</String>
	<String id="PicklistValue.Standard.taskSubject.Send Letter" source="Send Letter">Send Letter</String>
	<String id="PicklistValue.Standard.taskSubject.Send Quote" source="Send Quote">Send Quote</String>
	<String id="PicklistValue.Standard.workOrderStatus.Canceled" source="Canceled">Canceled</String>
	<String id="PicklistValue.Standard.workOrderStatus.Cannot Complete" source="Cannot Complete">Cannot Complete</String>
	<String id="PicklistValue.Standard.workOrderStatus.Closed" source="Closed">Closed</String>
	<String id="PicklistValue.Standard.workOrderStatus.Completed" source="Completed">Completed</String>
	<String id="PicklistValue.Standard.workOrderStatus.In Progress" source="In Progress">In Progress</String>
	<String id="PicklistValue.Standard.workOrderStatus.New" source="New">New</String>
	<String id="PicklistValue.Standard.workOrderStatus.On Hold" source="On Hold">On Hold</String>
	<String id="PicklistValue.Standard.workOrderPriority.Critical" source="Critical">Critical</String>
	<String id="PicklistValue.Standard.workOrderPriority.High" source="High">High</String>
	<String id="PicklistValue.Standard.workOrderPriority.Low" source="Low">Low</String>
	<String id="PicklistValue.Standard.workOrderPriority.Medium" source="Medium">Medium</String>
	<String id="PicklistValue.Standard.workOrderLineItemStatus.Canceled" source="Canceled">Canceled</String>
	<String id="PicklistValue.Standard.workOrderLineItemStatus.Cannot Complete" source="Cannot Complete">Cannot Complete</String>
	<String id="PicklistValue.Standard.workOrderLineItemStatus.Closed" source="Closed">Closed</String>
	<String id="PicklistValue.Standard.workOrderLineItemStatus.Completed" source="Completed">Completed</String>
	<String id="PicklistValue.Standard.workOrderLineItemStatus.In Progress" source="In Progress">In Progress</String>
	<String id="PicklistValue.Standard.workOrderLineItemStatus.New" source="New">New</String>
	<String id="PicklistValue.Standard.workOrderLineItemStatus.On Hold" source="On Hold">On Hold</String>
	<String id="PicklistValue.Standard.incidentRelatedItemImpactType.Business-Blocking" source="Business-Blocking">Business-Blocking</String>
	<String id="PicklistValue.Standard.incidentRelatedItemImpactType.Not Business-Blocking" source="Not Business-Blocking">Not Business-Blocking</String>
	<String id="PicklistValue.Standard.incidentRelatedItemImpactType.Partially Business-Blocking" source="Partially Business-Blocking">Partially Business-Blocking</String>
	<String id="PicklistValue.Standard.incidentRelatedItemImpactLevel.High" source="High">High</String>
	<String id="PicklistValue.Standard.incidentRelatedItemImpactLevel.Low" source="Low">Low</String>
	<String id="PicklistValue.Standard.incidentRelatedItemImpactLevel.Medium" source="Medium">Medium</String>
	<String id="PicklistValue.Standard.resourceAbsenceType.Medical" source="Medical">Medical</String>
	<String id="PicklistValue.Standard.resourceAbsenceType.Meeting" source="Meeting">Meeting</String>
	<String id="PicklistValue.Standard.resourceAbsenceType.Training" source="Training">Training</String>
	<String id="PicklistValue.Standard.resourceAbsenceType.Vacation" source="Vacation">Vacation</String>
	<String id="PicklistValue.Standard.problemRelatedItemImpactType.Business-Blocking" source="Business-Blocking">Business-Blocking</String>
	<String id="PicklistValue.Standard.problemRelatedItemImpactType.Not Business-Blocking" source="Not Business-Blocking">Not Business-Blocking</String>
	<String id="PicklistValue.Standard.problemRelatedItemImpactType.Partially Business-Blocking" source="Partially Business-Blocking">Partially Business-Blocking</String>
	<String id="PicklistValue.Standard.problemRelatedItemImpactLevel.High" source="High">High</String>
	<String id="PicklistValue.Standard.problemRelatedItemImpactLevel.Low" source="Low">Low</String>
	<String id="PicklistValue.Standard.problemRelatedItemImpactLevel.Medium" source="Medium">Medium</String>
	<String id="PicklistValue.Standard.changeRequestRelatedItemRelationType.Broke Item" source="Broke Item">Broke Item</String>
	<String id="PicklistValue.Standard.changeRequestRelatedItemRelationType.Fixed Item" source="Fixed Item">Fixed Item</String>
	<String id="PicklistValue.Standard.changeRequestRelatedItemImpactLevel.High" source="High">High</String>
	<String id="PicklistValue.Standard.changeRequestRelatedItemImpactLevel.Low" source="Low">Low</String>
	<String id="PicklistValue.Standard.changeRequestRelatedItemImpactLevel.Medium" source="Medium">Medium</String>
	<String id="PicklistValue.Standard.serviceAppointmentStatus.Canceled" source="Canceled">Canceled</String>
	<String id="PicklistValue.Standard.serviceAppointmentStatus.Cannot Complete" source="Cannot Complete">Cannot Complete</String>
	<String id="PicklistValue.Standard.serviceAppointmentStatus.Completed" source="Completed">Completed</String>
	<String id="PicklistValue.Standard.serviceAppointmentStatus.Dispatched" source="Dispatched">Dispatched</String>
	<String id="PicklistValue.Standard.serviceAppointmentStatus.In Progress" source="In Progress">In Progress</String>
	<String id="PicklistValue.Standard.serviceAppointmentStatus.None" source="None">None</String>
	<String id="PicklistValue.Standard.serviceAppointmentStatus.Scheduled" source="Scheduled">Scheduled</String>
	<String id="PicklistValue.Standard.salutation.Dr." source="Dr.">Dr.</String>
	<String id="PicklistValue.Standard.salutation.Mr." source="Mr.">Mr.</String>
	<String id="PicklistValue.Standard.salutation.Mrs." source="Mrs.">Mrs.</String>
	<String id="PicklistValue.Standard.salutation.Ms." source="Ms.">Ms.</String>
	<String id="PicklistValue.Standard.salutation.Prof." source="Prof.">Prof.</String>
	<String id="PicklistValue.Standard.quantityUnitOfMeasure.Each" source="Each">Each</String>
	<String id="PicklistValue.Standard.leadSource.Other" source="Other">Other</String>
	<String id="PicklistValue.Standard.leadSource.Partner Referral" source="Rfrence de partenaire">Rfrence de partenaire</String>
	<String id="PicklistValue.Standard.leadSource.Phone Inquiry" source="Demande tlphonique">Demande tlphonique</String>
	<String id="PicklistValue.Standard.leadSource.Purchased List" source="Liste achete">Liste achete</String>
	<String id="PicklistValue.Standard.leadSource.Web" source="la toile">la toile</String>
	<String id="PicklistValue.Standard.assetRelationshipType.Crossgrade" source="Crossgrade">Crossgrade</String>
	<String id="PicklistValue.Standard.assetRelationshipType.Replacement" source="Replacement">Replacement</String>
	<String id="PicklistValue.Standard.assetRelationshipType.Upgrade" source="Upgrade">Upgrade</String>
	<String id="PicklistValue.Standard.fieldBusinessStatus.Active" source="Active">Active</String>
	<String id="PicklistValue.Standard.fieldBusinessStatus.DeprecateCandidate" source="DeprecateCandidate">DeprecateCandidate</String>
	<String id="PicklistValue.Standard.fieldBusinessStatus.Hidden" source="Hidden">Hidden</String>
	<String id="PicklistValue.Standard.engagementActivityType.Email Hard Bounce" source="Email Hard Bounce">Email Hard Bounce</String>
	<String id="PicklistValue.Standard.engagementActivityType.Email Open" source="Email Open">Email Open</String>
	<String id="PicklistValue.Standard.engagementActivityType.Email Opt-in" source="Email Opt-in">Email Opt-in</String>
	<String id="PicklistValue.Standard.engagementActivityType.Email Preferences Open" source="Email Preferences Open">Email Preferences Open</String>
	<String id="PicklistValue.Standard.engagementActivityType.Email Send" source="Email Send">Email Send</String>
	<String id="PicklistValue.Standard.engagementActivityType.Email Soft Bounce" source="Email Soft Bounce">Email Soft Bounce</String>
	<String id="PicklistValue.Standard.engagementActivityType.Email Spam Complaint" source="Email Spam Complaint">Email Spam Complaint</String>
	<String id="PicklistValue.Standard.engagementActivityType.Email Unsubscribe" source="Email Unsubscribe">Email Unsubscribe</String>
	<String id="PicklistValue.Standard.engagementActivityType.Form Submit Error" source="Form Submit Error">Form Submit Error</String>
	<String id="PicklistValue.Standard.engagementActivityType.Form Submit Success" source="Form Submit Success">Form Submit Success</String>
	<String id="PicklistValue.Standard.engagementActivityType.Form View" source="Form View">Form View</String>
	<String id="PicklistValue.Standard.engagementActivityType.Landing Page Form Submit Error" source="Landing Page Form Submit Error">Landing Page Form Submit Error</String>
	<String id="PicklistValue.Standard.engagementActivityType.Landing Page Form Submit Success" source="Landing Page Form Submit Success">Landing Page Form Submit Success</String>
	<String id="PicklistValue.Standard.engagementActivityType.Landing Page View" source="Landing Page View">Landing Page View</String>
	<String id="PicklistValue.Standard.engagementActivityType.Link Click" source="Link Click">Link Click</String>
	<String id="PicklistValue.Standard.scorecardMetricCategory.Adoption" source="Adoption">Adoption</String>
	<String id="PicklistValue.Standard.scorecardMetricCategory.Field Enablement" source="Field Enablement">Field Enablement</String>
	<String id="PicklistValue.Standard.scorecardMetricCategory.Marketing" source="Marketing">Marketing</String>
	<String id="PicklistValue.Standard.scorecardMetricCategory.Sales" source="Sales">Sales</String>
	<String id="PicklistValue.Standard.scorecardMetricCategory.Support" source="Support">Support</String>
	<String id="RecordType.Metric.Completion" source="Completion">Completion</String>
	<String id="RecordType.Metric.Completion.Description" source="Measure achievement based on whether or not the metric is finished. Ideal for tracking milestones, or when you don't have metrics based on hard numbers. For example: Become Salesforce Certified.">Measure achievement based on whether or not the metric is finished. Ideal for tracking milestones, or when you don't have metrics based on hard numbers. For example: Become Salesforce Certified.</String>
	<String id="RecordType.Metric.Progress" source="Progress">Progress</String>
	<String id="RecordType.Metric.Progress.Description" source="Measure achievement based on how much is finished compared to a targeted value. Ideal for tracking hard numbers and percentages. For example: Convert 50 Leads or Achieve 100% Customer Satisfaction.">Measure achievement based on how much is finished compared to a targeted value. Ideal for tracking hard numbers and percentages. For example: Convert 50 Leads or Achieve 100% Customer Satisfaction.</String>
	<String id="ManagedContentType.cms_document" source="Document">Document</String>
	<String id="ManagedContentType.cms_document.Description" source="Add content using any file type or an external URL.">Add content using any file type or an external URL.</String>
	<String id="ManagedContentType.cms_image" source="Image">Image</String>
	<String id="ManagedContentType.cms_image.Description" source="Add media files, such as PNG or JPEG, or link to a URL.">Add media files, such as PNG or JPEG, or link to a URL.</String>
	<String id="ManagedContentType.news" source="News">News</String>
	<String id="ManagedContentType.news.Description" source="A basic article format with rich text and image support.">A basic article format with rich text and image support.</String>
	<String id="ManagedContentNodeType.null" source="MTEXT">MTEXT</String>
	<String id="ManagedContentNodeType.cms_document.altText.HelpText" source="Enter a brief description of the document.">Enter a brief description of the document.</String>
	<String id="ManagedContentNodeType.null" source="MEDIA">MEDIA</String>
	<String id="ManagedContentNodeType.cms_document.source.HelpText" source="Adds media to your content from a desktop file or URL link. Make sure the domain for your URL is allowed by your org so your users can access it.">Adds media to your content from a desktop file or URL link. Make sure the domain for your URL is allowed by your org so your users can access it.</String>
	<String id="ManagedContentNodeType.null" source="URL">URL</String>
	<String id="ManagedContentNodeType.cms_document.thumbUrl.HelpText" source="Links a thumbnail image to the content.">Links a thumbnail image to the content.</String>
	<String id="ManagedContentNodeType.null" source="NAMEFIELD">NAMEFIELD</String>
	<String id="ManagedContentNodeType.cms_document.title.HelpText" source="Enter the file name.">Enter the file name.</String>
	<String id="ManagedContentNodeType.null" source="MTEXT">MTEXT</String>
	<String id="ManagedContentNodeType.cms_image.altText.HelpText" source="Enter a brief description of the image.">Enter a brief description of the image.</String>
	<String id="ManagedContentNodeType.null" source="MEDIA">MEDIA</String>
	<String id="ManagedContentNodeType.cms_image.source.HelpText" source="Adds media to your content from a desktop file or URL link. Make sure the domain for your URL is allowed by your org so your users can access it.">Adds media to your content from a desktop file or URL link. Make sure the domain for your URL is allowed by your org so your users can access it.</String>
	<String id="ManagedContentNodeType.null" source="URL">URL</String>
	<String id="ManagedContentNodeType.cms_image.thumbUrl.HelpText" source="Links a thumbnail image to the content.">Links a thumbnail image to the content.</String>
	<String id="ManagedContentNodeType.null" source="NAMEFIELD">NAMEFIELD</String>
	<String id="ManagedContentNodeType.cms_image.title.HelpText" source="Enter the file name.">Enter the file name.</String>
	<String id="ManagedContentNodeType.null" source="IMG">IMG</String>
	<String id="ManagedContentNodeType.news.bannerImage.HelpText" source="Images arent required, but they help your post get attention.">Images arent required, but they help your post get attention.</String>
	<String id="ManagedContentNodeType.null" source="RTE">RTE</String>
	<String id="ManagedContentNodeType.null" source="MTEXT">MTEXT</String>
	<String id="ManagedContentNodeType.news.excerpt.HelpText" source="Excerpts display as summary or teaser text on compilation pages. Excerpts give your customers a quick sense of what your post is about so they can quickly decide whether or not to view the full article.">Excerpts display as summary or teaser text on compilation pages. Excerpts give your customers a quick sense of what your post is about so they can quickly decide whether or not to view the full article.</String>
	<String id="ManagedContentNodeType.news.excerpt.InfoMessage" source="Enter a summary or short description of your post...">Enter a summary or short description of your post...</String>
	<String id="ManagedContentNodeType.null" source="NAMEFIELD">NAMEFIELD</String>

</Media>
